odoo/addons/mgmtsystem_environment/README.rst
odoo/addons/mgmtsystem_environment/__init__.py
odoo/addons/mgmtsystem_environment/__manifest__.py
odoo/addons/mgmtsystem_environment/data/environment.xml
odoo/addons/mgmtsystem_environment/i18n/de.po
odoo/addons/mgmtsystem_environment/i18n/fr.po
odoo/addons/mgmtsystem_environment/i18n/it.po
odoo/addons/mgmtsystem_environment/i18n/mgmtsystem_environment.pot
odoo/addons/mgmtsystem_environment/i18n/nb.po
odoo/addons/mgmtsystem_environment/i18n/pt_BR.po
odoo/addons/mgmtsystem_environment/i18n/sv.po
odoo/addons/mgmtsystem_environment/i18n/tr.po
odoo/addons/mgmtsystem_environment/i18n/vi.po
odoo/addons/mgmtsystem_environment/readme/CONFIGURE.rst
odoo/addons/mgmtsystem_environment/readme/CONTRIBUTORS.rst
odoo/addons/mgmtsystem_environment/readme/DESCRIPTION.rst
odoo/addons/mgmtsystem_environment/readme/USAGE.rst
odoo/addons/mgmtsystem_environment/static/description/icon.png
odoo/addons/mgmtsystem_environment/static/description/index.html
odoo/addons/mgmtsystem_environment/static/src/img/icon.png
odoo_addon_mgmtsystem_environment-16.0.1.0.0.3.dist-info/METADATA
odoo_addon_mgmtsystem_environment-16.0.1.0.0.3.dist-info/WHEEL
odoo_addon_mgmtsystem_environment-16.0.1.0.0.3.dist-info/top_level.txt
odoo_addon_mgmtsystem_environment-16.0.1.0.0.3.dist-info/RECORD
